playerloop/__init__.py
playerloop/playerloop.py
playerloop-0.0.1.dist-info/LICENSE
playerloop-0.0.1.dist-info/METADATA
playerloop-0.0.1.dist-info/WHEEL
playerloop-0.0.1.dist-info/top_level.txt
playerloop-0.0.1.dist-info/RECORD
